yta_video_advanced_premades/__init__.py
yta_video_advanced_premades/google_search.py
yta_video_advanced_premades/resources/__init__.py
yta_video_advanced_premades/resources/image/__init__.py
yta_video_advanced_premades/resources/image/drive_urls.py
yta_video_advanced_premades/social_networks/__init__.py
yta_video_advanced_premades/social_networks/discord/__init__.py
yta_video_advanced_premades/social_networks/discord/classes/__init__.py
yta_video_advanced_premades/social_networks/discord/classes/discord_conversation_character.py
yta_video_advanced_premades/social_networks/discord/classes/discord_conversation_message.py
yta_video_advanced_premades/social_networks/discord/constants.py
yta_video_advanced_premades/social_networks/discord/discord_conversation_video_generator.py
yta_video_advanced_premades/social_networks/discord/enums.py
yta_video_advanced_premades/youtube_search.py
yta_video_advanced_premades-0.0.1.dist-info/LICENSE
yta_video_advanced_premades-0.0.1.dist-info/METADATA
yta_video_advanced_premades-0.0.1.dist-info/WHEEL
yta_video_advanced_premades-0.0.1.dist-info/RECORD
