Metadata-Version: 2.3
Name: yta-video-advanced-premades
Version: 0.0.1
Summary: Youtube Autonomous Advanced Video Premades Module.
Author: danialcala94
Author-email: danielalcalavalera@gmail.com
Requires-Python: ==3.9
Classifier: Programming Language :: Python :: 3
Classifier: Programming Language :: Python :: 3.9
Requires-Dist: yta_video_base (>=0.0.1,<1.0.0)
